screw_bolt/__init__.py
zen_screw_bolt-1.0.2.dist-info/METADATA
zen_screw_bolt-1.0.2.dist-info/WHEEL
zen_screw_bolt-1.0.2.dist-info/top_level.txt
zen_screw_bolt-1.0.2.dist-info/RECORD
