Metadata-Version: 2.1
Name: zen-screw-bolt
Version: 1.0.2
Summary: Screw bolt builder for ZenCAD
Home-page: https://gitlab.com/hnau_zen/screw_bolt
Author: Mark Zorikhin
Author-email: hnau256@gmail.com
License: UNKNOWN
Platform: UNKNOWN
Classifier: Programming Language :: Python :: 3
Classifier: License :: OSI Approved :: MIT License
Classifier: Operating System :: OS Independent
Requires-Python: >=3.6
